soft_webauthn_patched.py
ubank.py
ubank-2.2.5.dist-info/METADATA
ubank-2.2.5.dist-info/WHEEL
ubank-2.2.5.dist-info/entry_points.txt
ubank-2.2.5.dist-info/licenses/LICENSE
ubank-2.2.5.dist-info/RECORD
