Metadata-Version: 2.4
Name: ubank
Version: 2.2.5
Summary: Access ubank.com.au with Python
Author: eidorb
License-Expression: MIT
License-File: LICENSE
Requires-Python: >=3.11
Requires-Dist: httpx>=0.28.1
Requires-Dist: meatie>=0.1.20
Requires-Dist: pydantic>=2.12.0
Requires-Dist: soft-webauthn>=0.1.4
